LICENSE
MANIFEST.in
README
pre-commit
pre-commit.conf
setup.py
svnplus/__init__.py
svnplus/tagprotect.py
svnplus.egg-info/PKG-INFO
svnplus.egg-info/SOURCES.txt
svnplus.egg-info/dependency_links.txt
svnplus.egg-info/not-zip-safe
svnplus.egg-info/top_level.txt