Metadata-Version: 1.1
Name: svnplus
Version: 3.19.1
Summary: This is a subversion hook.  It provides a protection mechanism for subversion repositories so that previously committed "tags" are immutable.
Home-page: https://github.com/ossCare/svnPlus
Author: Joseph C. Pietras
Author-email: joseph.pietras@gmail.com
License: Apache Software License 2.0
Keywords: subversion hook tagprotect immutable
Platform: UNKNOWN
Classifier: Intended Audience :: Information Technology
Classifier: License :: OSI Approved :: Apache Software License
Classifier: Natural Language :: English
